repo_to_one_file/__init__.py
repo_to_one_file/__main__.py
repo_to_one_file-1.0.1.dist-info/LICENSE
repo_to_one_file-1.0.1.dist-info/METADATA
repo_to_one_file-1.0.1.dist-info/WHEEL
repo_to_one_file-1.0.1.dist-info/entry_points.txt
repo_to_one_file-1.0.1.dist-info/top_level.txt
repo_to_one_file-1.0.1.dist-info/RECORD
