Metadata-Version: 2.1
Name: repo-to-one-file
Version: 1.0.1
Summary: A tool to consolidate repository files into a single file
Home-page: https://github.com/tonypls/repo-to-one-file
Author: tonypls
Author-email: tony@appy.co.nz
Classifier: Development Status :: 3 - Alpha
Classifier: Intended Audience :: Developers
Classifier: License :: OSI Approved :: MIT License
Classifier: Operating System :: OS Independent
Classifier: Programming Language :: Python :: 3
Classifier: Programming Language :: Python :: 3.7
Classifier: Programming Language :: Python :: 3.8
Classifier: Programming Language :: Python :: 3.9
Classifier: Programming Language :: Python :: 3.10
Requires-Python: >=3.7
License-File: LICENSE
